JingtongGoMasteringGoZhongwenbanFix1/README.md
JingtongGoMasteringGoZhongwenbanFix1/__init__.py
JingtongGoMasteringGoZhongwenbanFix1/__main__.py
JingtongGoMasteringGoZhongwenbanFix1/file.epub
JingtongGoMasteringGoZhongwenbanFix1/index.html
JingtongGoMasteringGoZhongwenbanFix1/css/__init__.py
JingtongGoMasteringGoZhongwenbanFix1/css/annotations.css
JingtongGoMasteringGoZhongwenbanFix1/css/main.css
JingtongGoMasteringGoZhongwenbanFix1/css/normalize.css
JingtongGoMasteringGoZhongwenbanFix1/css/popup.css
JingtongGoMasteringGoZhongwenbanFix1/font/__init__.py
JingtongGoMasteringGoZhongwenbanFix1/font/fontello.eot
JingtongGoMasteringGoZhongwenbanFix1/font/fontello.svg
JingtongGoMasteringGoZhongwenbanFix1/font/fontello.ttf
JingtongGoMasteringGoZhongwenbanFix1/font/fontello.woff
JingtongGoMasteringGoZhongwenbanFix1/img/__init__.py
JingtongGoMasteringGoZhongwenbanFix1/img/annotator-glyph-sprite.png
JingtongGoMasteringGoZhongwenbanFix1/img/annotator-icon-sprite.png
JingtongGoMasteringGoZhongwenbanFix1/img/apple-touch-icon.png
JingtongGoMasteringGoZhongwenbanFix1/img/cancelfullscreen.png
JingtongGoMasteringGoZhongwenbanFix1/img/close.png
JingtongGoMasteringGoZhongwenbanFix1/img/fullscreen.png
JingtongGoMasteringGoZhongwenbanFix1/img/loader.gif
JingtongGoMasteringGoZhongwenbanFix1/img/menu-icon.png
JingtongGoMasteringGoZhongwenbanFix1/img/save.png
JingtongGoMasteringGoZhongwenbanFix1/img/saved.png
JingtongGoMasteringGoZhongwenbanFix1/img/settings-s.png
JingtongGoMasteringGoZhongwenbanFix1/img/settings.png
JingtongGoMasteringGoZhongwenbanFix1/img/star.png
JingtongGoMasteringGoZhongwenbanFix1/js/__init__.py
JingtongGoMasteringGoZhongwenbanFix1/js/epub.js
JingtongGoMasteringGoZhongwenbanFix1/js/epub.min.js
JingtongGoMasteringGoZhongwenbanFix1/js/epub.min.map
JingtongGoMasteringGoZhongwenbanFix1/js/hooks.min.js
JingtongGoMasteringGoZhongwenbanFix1/js/hooks.min.map
JingtongGoMasteringGoZhongwenbanFix1/js/reader.js
JingtongGoMasteringGoZhongwenbanFix1/js/reader.js.map
jingtong_go_mastering_go_zhongwenban_fix1-2025.3.24.0.dist-info/METADATA
jingtong_go_mastering_go_zhongwenban_fix1-2025.3.24.0.dist-info/WHEEL
jingtong_go_mastering_go_zhongwenban_fix1-2025.3.24.0.dist-info/entry_points.txt
jingtong_go_mastering_go_zhongwenban_fix1-2025.3.24.0.dist-info/top_level.txt
jingtong_go_mastering_go_zhongwenban_fix1-2025.3.24.0.dist-info/RECORD
